odoo_build/__init__.py
odoo_build/argument_parser.py
odoo_build/command.py
odoo_build/console.py
odoo_build/database.py
odoo_build/obuild
odoo_build-4.0.5.data/scripts/obuild
odoo_build-4.0.5.dist-info/LICENSE
odoo_build-4.0.5.dist-info/METADATA
odoo_build-4.0.5.dist-info/WHEEL
odoo_build-4.0.5.dist-info/top_level.txt
odoo_build-4.0.5.dist-info/RECORD
