Metadata-Version: 2.1
Name: odoo-build
Version: 4.0.5
Summary: An utility to manage Odoo pip build
Home-page: https://bitbucket.org/bluestarsolutions/odoo-build
Author: Bluestar Solutions Sàrl
Author-email: devs@bluestar.solutions
License: UNKNOWN
Platform: UNKNOWN
Classifier: Programming Language :: Python
Classifier: Development Status :: 5 - Production/Stable
Classifier: License :: OSI Approved :: GNU General Public License v3 (GPLv3)
Classifier: Intended Audience :: Developers
Classifier: Natural Language :: English
Classifier: Operating System :: POSIX :: Linux
Classifier: Programming Language :: Python :: 3.6
Classifier: Topic :: Software Development :: Build Tools
Requires-Python: >=3.6
License-File: LICENSE
Requires-Dist: setuptools
Requires-Dist: setuptools-odoo
Requires-Dist: psycopg2-binary
Requires-Dist: argcomplete
Requires-Dist: colorama
Requires-Dist: pyyaml
